CHANGES.txt
LICENSE.txt
MANIFEST.in
README.txt
setup.py
src/j01/__init__.py
src/j01.datetimepicker.egg-info/PKG-INFO
src/j01.datetimepicker.egg-info/SOURCES.txt
src/j01.datetimepicker.egg-info/dependency_links.txt
src/j01.datetimepicker.egg-info/namespace_packages.txt
src/j01.datetimepicker.egg-info/not-zip-safe
src/j01.datetimepicker.egg-info/requires.txt
src/j01.datetimepicker.egg-info/top_level.txt
src/j01/datetimepicker/README.txt
src/j01/datetimepicker/__init__.py
src/j01/datetimepicker/browser.zcml
src/j01/datetimepicker/configure.zcml
src/j01/datetimepicker/converter.py
src/j01/datetimepicker/input.pt
src/j01/datetimepicker/interfaces.py
src/j01/datetimepicker/widget.py
src/j01/datetimepicker/css/j01.datetimepicker.css
src/j01/datetimepicker/css/j01.datetimepicker.min.css
src/j01/datetimepicker/js/bootstrap-collapse.js
src/j01/datetimepicker/js/bootstrap-transition.js
src/j01/datetimepicker/js/j01.datetimepicker.js
src/j01/datetimepicker/js/j01.datetimepicker.min.js
src/j01/datetimepicker/js/locales.js
src/j01/datetimepicker/js/locales.min.js
src/j01/datetimepicker/js/moment-with-locales.js
src/j01/datetimepicker/js/moment-with-locales.min.js
src/j01/datetimepicker/js/moment.js
src/j01/datetimepicker/js/moment.min.js
src/j01/datetimepicker/js/locale/af.js
src/j01/datetimepicker/js/locale/ar-dz.js
src/j01/datetimepicker/js/locale/ar-kw.js
src/j01/datetimepicker/js/locale/ar-ly.js
src/j01/datetimepicker/js/locale/ar-ma.js
src/j01/datetimepicker/js/locale/ar-sa.js
src/j01/datetimepicker/js/locale/ar-tn.js
src/j01/datetimepicker/js/locale/ar.js
src/j01/datetimepicker/js/locale/az.js
src/j01/datetimepicker/js/locale/be.js
src/j01/datetimepicker/js/locale/bg.js
src/j01/datetimepicker/js/locale/bm.js
src/j01/datetimepicker/js/locale/bn.js
src/j01/datetimepicker/js/locale/bo.js
src/j01/datetimepicker/js/locale/br.js
src/j01/datetimepicker/js/locale/bs.js
src/j01/datetimepicker/js/locale/ca.js
src/j01/datetimepicker/js/locale/cs.js
src/j01/datetimepicker/js/locale/cv.js
src/j01/datetimepicker/js/locale/cy.js
src/j01/datetimepicker/js/locale/da.js
src/j01/datetimepicker/js/locale/de-at.js
src/j01/datetimepicker/js/locale/de-ch.js
src/j01/datetimepicker/js/locale/de.js
src/j01/datetimepicker/js/locale/dv.js
src/j01/datetimepicker/js/locale/el.js
src/j01/datetimepicker/js/locale/en-au.js
