Metadata-Version: 1.1
Name: j01.datetimepicker
Version: 0.5.0
Summary: Bootstrap 3 datetimepicker based on z3c.form for Zope 3
Home-page: http://pypi.python.org/pypi/j01.datetimepicker
Author: Roger Ineichen, Projekt01 GmbH
Author-email: dev@projekt01.ch
License: ZPL 2.1
Keywords: J01 JQuery bootstrap datetime picker z3c form widget Zope3
Platform: UNKNOWN
Classifier: Development Status :: 5 - Production/Stable
Classifier: Environment :: Web Environment
Classifier: Intended Audience :: Developers
Classifier: License :: OSI Approved :: Zope Public License
Classifier: Programming Language :: Python
Classifier: Natural Language :: English
Classifier: Operating System :: OS Independent
Classifier: Topic :: Internet :: WWW/HTTP
Classifier: Framework :: Zope3
